mlhp.py
pbf.py
pymlhpbf.cpython-311-i386-linux-musl.so
pymlhpcore.cpython-311-i386-linux-musl.so
pbf-0.2.0.dist-info/WHEEL
pbf-0.2.0.dist-info/METADATA
pbf-0.2.0.dist-info/RECORD
pbf-0.2.0.dist-info/licenses/LICENSE
pbf.libs/libstdc++-d2a021ba.so.6.0.32
pbf.libs/libgcc_s-f3fb5a36.so.1
pbf.libs/libgomp-aa3e8c56.so.1.0.0
