Metadata-Version: 2.2
Name: pbf
Version: 0.2.0
Summary: A work-in-progress powder bed fusion simulation library.
Author: Philipp Kopp, Massimo Carraturo
Classifier: License :: OSI Approved :: MIT License
